lancealot/__about__.py
lancealot/__init__.py
lancealot-0.0.1.dist-info/METADATA
lancealot-0.0.1.dist-info/WHEEL
lancealot-0.0.1.dist-info/licenses/LICENSE
lancealot-0.0.1.dist-info/licenses/LICENSE.txt
lancealot-0.0.1.dist-info/RECORD
